viminit/__init__.py
viminit-0.3.data/scripts/viminit
viminit-0.3.dist-info/DESCRIPTION.rst
viminit-0.3.dist-info/METADATA
viminit-0.3.dist-info/RECORD
viminit-0.3.dist-info/WHEEL
viminit-0.3.dist-info/metadata.json
viminit-0.3.dist-info/top_level.txt
