Metadata-Version: 2.0
Name: viminit
Version: 0.3
Summary: Set up a vimlang plugin project directory.
Home-page: http://github.com/vmchale/viminit
Author: Vanessa McHale
Author-email: tmchale@wisc.edu
License: BSD3
Platform: UNKNOWN
Requires-Dist: gitpython
